datasanity/__init__.py
datasanity/core.py
datasanity/report.py
datasanity-0.1.0.dist-info/licenses/LICENSE
tests/__init__.py
tests/test_core.py
datasanity-0.1.0.dist-info/METADATA
datasanity-0.1.0.dist-info/WHEEL
datasanity-0.1.0.dist-info/top_level.txt
datasanity-0.1.0.dist-info/RECORD
