Metadata-Version: 2.4
Name: datasanity
Version: 0.1.0
Summary: A tiny (<200 loc) CSV health + anomaly detector
Author: RJ Sabouhi
License: MIT License
Project-URL: Homepage, https://github.com/rjsabouhi/datasanity
Project-URL: Repository, https://github.com/rjsabouhi/datasanity
Requires-Python: >=3.8
License-File: LICENSE
Requires-Dist: pandas
Requires-Dist: numpy
Dynamic: license-file
